<?xml version="1.0" encoding="utf-8" ?>
<odoo>
    <data>
        <record id="phongbenh_information_form_view" model="ir.ui.view">            <!--view phong benh -->
            <field name="name">Phòng Bệnh View</field>
            <field name="model">benhvien.phongbenh</field>
            <field name="arch" type="xml">
                <list>
                    <field name="ma_phong"/>
                    <field name="name"/>
                    <field name="khoa"/>
                    <field name="bed_count"/>
                </list>
            </field>
        </record>
    </data>
</odoo>